_version.py
supspec/__init__.py
supspec/run.py
supspec/support_functions/import_data.py
supspec/support_functions/mcmc_fitting.py
supspec/support_functions/plot.py
supspec/support_functions/support_functions.py
supspec-1.0.9.dist-info/.DS_Store
supspec-1.0.9.dist-info/METADATA
supspec-1.0.9.dist-info/WHEEL
supspec-1.0.9.dist-info/entry_points.txt
supspec-1.0.9.dist-info/top_level.txt
supspec-1.0.9.dist-info/RECORD
