Metadata-Version: 2.1
Name: supspec
Version: 1.0.9
Author-email: Karthik Yadavalli <karthik.yadavalli@cfa.harvard.edu>, Ivy Yao <karthik.yadavalli@cfa.harvard.edu>, Nahum Linhart <karthik.yadavalli@cfa.harvard.edu>
Classifier: Development Status :: 4 - Beta
Classifier: License :: OSI Approved :: MIT License
Classifier: Intended Audience :: Developers
Classifier: Intended Audience :: Science/Research
Classifier: Operating System :: OS Independent
Classifier: Programming Language :: Python
Requires-Python: >=3.9
Requires-Dist: numpy >=1.0
Requires-Dist: pandas
Requires-Dist: emcee
Requires-Dist: corner
Requires-Dist: matplotlib
Requires-Dist: tqdm
Requires-Dist: scipy
Requires-Dist: argparse
Provides-Extra: dev
